desktop.ini
example/__init__.py
example/_statistics.py
example/grasia.py
example/ineqpy.py
example/statistics.py
example/utils.py
inequalipy/__init__.py
inequalipy/atkinson.py
inequalipy/gini.py
inequalipy/kolmpollak.py
inequipy/__init__.py
inequipy/atkinson.py
inequipy/gini.py
inequipy/inequipy.py
inequipy/kolmpollak.py
inequalipy-1.0.5.dist-info/LICENSE
inequalipy-1.0.5.dist-info/METADATA
inequalipy-1.0.5.dist-info/WHEEL
inequalipy-1.0.5.dist-info/top_level.txt
inequalipy-1.0.5.dist-info/RECORD
