Metadata-Version: 2.1
Name: inequalipy
Version: 1.0.5
Summary: Inequalipy contains functions for the Kolm-Pollak, Atkinson and Gini Index aproaches to calculating inequality of a distribution
Home-page: https://github.com/urutau-nz/inequalipy
Author: Tom Logan, Mitchell Anderson
Author-email: tom.logan@canterbury.ac.nz
License: UNKNOWN
Platform: UNKNOWN
Classifier: Programming Language :: Python :: 3
Classifier: License :: OSI Approved :: MIT License
Classifier: Operating System :: OS Independent
Requires-Python: >=3
Requires-Dist: numpy
